pyquokka/__init__.py
pyquokka/catalog.py
pyquokka/common_startup.sh
pyquokka/coordinator.py
pyquokka/core.py
pyquokka/dataset.py
pyquokka/datastream.py
pyquokka/debugger.py
pyquokka/df.py
pyquokka/disk_setup.sh
pyquokka/executors.py
pyquokka/expression.py
pyquokka/flight.py
pyquokka/hbq.py
pyquokka/ldb.so
pyquokka/leader_start_ray.sh
pyquokka/leader_startup.sh
pyquokka/logical.py
pyquokka/orderedstream.py
pyquokka/placement_strategy.py
pyquokka/quokka_dataset.py
pyquokka/quokka_runtime.py
pyquokka/redis.conf
pyquokka/sql.py
pyquokka/sql_utils.py
pyquokka/state.py
pyquokka/tables.py
pyquokka/target_info.py
pyquokka/task.py
pyquokka/utils.py
pyquokka/windowtypes.py
pyquokka/dataset/__init__.py
pyquokka/dataset/base_dataset.py
pyquokka/dataset/crypto_dataset.py
pyquokka/dataset/ordered_readers.py
pyquokka/dataset/unordered_readers.py
pyquokka/executors/__init__.py
pyquokka/executors/base_executor.py
pyquokka/executors/cep_executors.py
pyquokka/executors/sql_executors.py
pyquokka/executors/ts_executors.py
pyquokka/executors/vector_executors.py
pyquokka-0.3.2.dist-info/LICENSE
pyquokka-0.3.2.dist-info/METADATA
pyquokka-0.3.2.dist-info/WHEEL
pyquokka-0.3.2.dist-info/entry_points.txt
pyquokka-0.3.2.dist-info/top_level.txt
pyquokka-0.3.2.dist-info/RECORD
