Metadata-Version: 2.1
Name: pyquokka
Version: 0.3.2
Summary: Quokka
Author: Tony Wang
Author-email: zihengw@stanford.edu
License: http://www.apache.org/licenses/LICENSE-2.0
Keywords: python
Platform: UNKNOWN
Classifier: Development Status :: 3 - Alpha
Classifier: Programming Language :: Python :: 3
Classifier: Operating System :: MacOS :: MacOS X
Classifier: Operating System :: POSIX :: Linux
License-File: LICENSE
Requires-Dist: cffi
Requires-Dist: pyarrow
Requires-Dist: duckdb (>=0.6.0)
Requires-Dist: redis
Requires-Dist: boto3
Requires-Dist: numpy
Requires-Dist: pandas
Requires-Dist: protobuf
Requires-Dist: ray (>=2.0.0)
Requires-Dist: psutil
Requires-Dist: polars (>=0.17.0)
Requires-Dist: sqlglot (>=11.4.2)
Requires-Dist: graphviz
Requires-Dist: tqdm
Requires-Dist: aiohttp
Requires-Dist: botocore
Requires-Dist: threadpoolctl
